{
  "indexes": [
    {
      "collectionGroup": "events",
      "queryScope": "COLLECTION",
      "fields": [
        {
          "fieldPath": "circleId",
          "order": "ASCENDING"
        },
        {
          "fieldPath": "datetime",
          "order": "ASCENDING"
        }
      ]
    },
    {
      "collectionGroup": "payments",
      "queryScope": "COLLECTION",
      "fields": [
        {
          "fieldPath": "userId",
          "order": "ASCENDING"
        },
        {
          "fieldPath": "status",
          "order": "ASCENDING"
        }
      ]
    },
    {
      "collectionGroup": "notifications",
      "queryScope": "COLLECTION",
      "fields": [
        {
          "fieldPath": "circleId",
          "order": "ASCENDING"
        },
        {
          "fieldPath": "sentAt",
          "order": "DESCENDING"
        }
      ]
    }
  ],
  "fieldOverrides": []
}
